mj_rag/__init__.py
mj_rag/algorithm.py
mj_rag/dummy.py
mj_rag/interfaces.py
mj_rag/litellm/__init__.py
mj_rag/litellm/llm_service.py
mj_rag/milvus/__init__.py
mj_rag/milvus/vector_db_service.py
mj_rag-0.1.0.dist-info/METADATA
mj_rag-0.1.0.dist-info/WHEEL
mj_rag-0.1.0.dist-info/RECORD
